[
  {
    "id": 1,
    "firstName": "Alice",
    "lastName": "Johnson",
    "email": "alice.johnson@email.com",
    "phone": "+1-555-0101",
    "address": "123 Main Street",
    "city": "New York",
    "state": "NY",
    "zipCode": "10001",
    "company": "Johnson & Associates",
    "isActive": true,
    "createdAt": "2024-01-01T00:00:00.000Z",
    "updatedAt": "2024-01-15T10:00:00.000Z"
  },
  {
    "id": 2,
    "firstName": "Bob",
    "lastName": "Smith",
    "email": "bob.smith@email.com",
    "phone": "+1-555-0102",
    "address": "456 Oak Avenue",
    "city": "Los Angeles",
    "state": "CA",
    "zipCode": "90210",
    "company": "Smith Enterprises",
    "isActive": true,
    "createdAt": "2024-01-02T00:00:00.000Z",
    "updatedAt": "2024-01-15T10:00:00.000Z"
  },
  {
    "id": 3,
    "firstName": "Carol",
    "lastName": "Davis",
    "email": "carol.davis@email.com",
    "phone": "+1-555-0103",
    "address": "789 Pine Street",
    "city": "Chicago",
    "state": "IL",
    "zipCode": "60601",
    "company": "Davis Consulting",
    "isActive": true,
    "createdAt": "2024-01-03T00:00:00.000Z",
    "updatedAt": "2024-01-15T10:00:00.000Z"
  },
  {
    "id": 4,
    "firstName": "David",
    "lastName": "Wilson",
    "email": "david.wilson@email.com",
    "phone": "+1-555-0104",
    "address": "321 Elm Drive",
    "city": "Houston",
    "state": "TX",
    "zipCode": "77001",
    "company": "Wilson Industries",
    "isActive": true,
    "createdAt": "2024-01-04T00:00:00.000Z",
    "updatedAt": "2024-01-15T10:00:00.000Z"
  },
  {
    "id": 5,
    "firstName": "Eva",
    "lastName": "Brown",
    "email": "eva.brown@email.com",
    "phone": "+1-555-0105",
    "address": "654 Maple Lane",
    "city": "Phoenix",
    "state": "AZ",
    "zipCode": "85001",
    "company": "Brown Solutions",
    "isActive": true,
    "createdAt": "2024-01-05T00:00:00.000Z",
    "updatedAt": "2024-01-15T10:00:00.000Z"
  },
  {
    "id": 6,
    "firstName": "Frank",
    "lastName": "Miller",
    "email": "frank.miller@email.com",
    "phone": "+1-555-0106",
    "address": "987 Cedar Road",
    "city": "Philadelphia",
    "state": "PA",
    "zipCode": "19101",
    "company": "Miller Corp",
    "isActive": true,
    "createdAt": "2024-01-06T00:00:00.000Z",
    "updatedAt": "2024-01-15T10:00:00.000Z"
  },
  {
    "id": 7,
    "firstName": "Grace",
    "lastName": "Taylor",
    "email": "grace.taylor@email.com",
    "phone": "+1-555-0107",
    "address": "147 Birch Street",
    "city": "San Antonio",
    "state": "TX",
    "zipCode": "78201",
    "company": "Taylor Group",
    "isActive": true,
    "createdAt": "2024-01-07T00:00:00.000Z",
    "updatedAt": "2024-01-15T10:00:00.000Z"
  },
  {
    "id": 8,
    "firstName": "Henry",
    "lastName": "Anderson",
    "email": "henry.anderson@email.com",
    "phone": "+1-555-0108",
    "address": "258 Spruce Avenue",
    "city": "San Diego",
    "state": "CA",
    "zipCode": "92101",
    "company": "Anderson LLC",
    "isActive": true,
    "createdAt": "2024-01-08T00:00:00.000Z",
    "updatedAt": "2024-01-15T10:00:00.000Z"
  },
  {
    "id": 9,
    "firstName": "Ivy",
    "lastName": "Thomas",
    "email": "ivy.thomas@email.com",
    "phone": "+1-555-0109",
    "address": "369 Willow Way",
    "city": "Dallas",
    "state": "TX",
    "zipCode": "75201",
    "company": "Thomas Ventures",
    "isActive": true,
    "createdAt": "2024-01-09T00:00:00.000Z",
    "updatedAt": "2024-01-15T10:00:00.000Z"
  },
  {
    "id": 10,
    "firstName": "Jack",
    "lastName": "Jackson",
    "email": "jack.jackson@email.com",
    "phone": "+1-555-0110",
    "address": "741 Poplar Place",
    "city": "San Jose",
    "state": "CA",
    "zipCode": "95101",
    "company": "Jackson Holdings",
    "isActive": true,
    "createdAt": "2024-01-10T00:00:00.000Z",
    "updatedAt": "2024-01-15T10:00:00.000Z"
  }
]
